b3j0f/__init__.py
b3j0f/utils/__init__.py
b3j0f/utils/chaining.py
b3j0f/utils/citerable.so
b3j0f/utils/iterable.py
b3j0f/utils/path.py
b3j0f/utils/property.py
b3j0f/utils/proxy.py
b3j0f/utils/reflect.py
b3j0f/utils/runtime.py
b3j0f/utils/ut.py
b3j0f/utils/version.py
b3j0f/utils/test/__init__.py
b3j0f/utils/test/chaining.py
b3j0f/utils/test/iterable.py
b3j0f/utils/test/path.py
b3j0f/utils/test/property.py
b3j0f/utils/test/proxy.py
b3j0f/utils/test/reflect.py
b3j0f/utils/test/runtime.py
b3j0f/utils/test/ut.py
b3j0f.utils-1.4.4.dist-info/DESCRIPTION.rst
b3j0f.utils-1.4.4.dist-info/METADATA
b3j0f.utils-1.4.4.dist-info/RECORD
b3j0f.utils-1.4.4.dist-info/WHEEL
b3j0f.utils-1.4.4.dist-info/metadata.json
b3j0f.utils-1.4.4.dist-info/top_level.txt
