Metadata-Version: 2.0
Name: b3j0f.utils
Version: 1.4.4
Summary: Set of tools and utilities useful in python projects
Home-page: https://github.com/b3j0f/utils
Author: b3j0f
Author-email: ib3j0f@gmail.com
License: MIT License
Keywords: utils,chaining,iterable,tools,path,property,dynamic,reflection,reflect,runtime,unittest,unit test,version,common
Platform: UNKNOWN
Classifier: Development Status :: 5 - Production/Stable
Classifier: License :: OSI Approved :: MIT License
Classifier: Natural Language :: French
Classifier: Operating System :: OS Independent
Classifier: Topic :: Utilities
Classifier: Topic :: Software Development :: Libraries :: Python Modules
Classifier: Intended Audience :: Developers
Classifier: Programming Language :: Python
Classifier: Programming Language :: Python :: 2.6
Classifier: Programming Language :: Python :: 2.7
Classifier: Programming Language :: Python :: 3
Classifier: Programming Language :: Python :: 3.0
Classifier: Programming Language :: Python :: 3.1
Classifier: Programming Language :: Python :: 3.2
Classifier: Programming Language :: Python :: 3.3
Classifier: Programming Language :: Python :: 3.4
Classifier: Programming Language :: Python :: 3.5
Classifier: Programming Language :: Python :: Implementation :: CPython
Requires-Dist: six
Requires-Dist: ordereddict
